[{"fileName":"mall_V1.4.8.11_uat.apk","fileSize":14047206,"createTime":1539770348200,"versionName":"1.4.8.11","appLabel":"即有生活","appPkgName":"com.giveu.shoppingmall","appMd5":"b0f46fafd6085af6086980479a188f6d","versionCode":"10407"},{"fileName":"mall_V2.0.1_online.apk","fileSize":13444481,"createTime":1540381074983,"versionName":"2.0.1","appLabel":"即有生活","appPkgName":"com.giveu.shoppingmall","appMd5":"6ee906b605cc1452e6664b2314435d8c","versionCode":"20001","updateContent":"1.正式版本V2.0.1\n2.会员一期遗留问题修复\n"},{"fileName":"mall_V2.0.2_online.apk","fileSize":13450826,"createTime":1540996736225,"versionName":"2.0.2","appLabel":"即有生活","appPkgName":"com.giveu.shoppingmall","appMd5":"e2f08947b9f828047cd057c3e02c2cfb","versionCode":"20002","updateContent":"1.正式版本V2.0.2\n2.新增会员三期功能\n3.功能优化调整\n"},{"fileName":"mall_V2.0.3_online.apk","fileSize":13371520,"createTime":1541601166532,"versionName":"2.0.3","appLabel":"即有生活","appPkgName":"com.giveu.shoppingmall","appMd5":"fb590293b776022ef176d33c8b940ce7","versionCode":"20003"},{"fileName":"mall_V2.0.4_online.apk","fileSize":13201405,"createTime":1542351089075,"versionName":"2.0.4","appLabel":"即有生活","appPkgName":"com.giveu.shoppingmall","appMd5":"b9940233bd81a8a25bfccbd90a498f35","versionCode":"20004"},{"fileName":"mall_V2.0.5_online.apk","fileSize":14375199,"createTime":1542809470701,"versionName":"2.0.5","appLabel":"即有生活","appPkgName":"com.giveu.shoppingmall","appMd5":"7f9f8262d6b1c255b17afeb17eb019fc","versionCode":"20005"},{"fileName":"mall_V2.0.6_online.apk","fileSize":16849730,"createTime":1543511841027,"versionName":"2.0.6","appLabel":"即有生活","appPkgName":"com.giveu.shoppingmall","appMd5":"a11bc20e7d72f11494e01370238e73da","versionCode":"20006"},{"fileName":"mall_V2.0.7_online.apk","fileSize":16843891,"createTime":1544107662146,"versionName":"2.0.7","appLabel":"即有生活","appPkgName":"com.giveu.shoppingmall","appMd5":"966aa521315bb688772cbae106b49a14","versionCode":"20007","updateContent":"1.V2.0.7正式包\n2.更新优化退回功能\n3.bug修复"},{"fileName":"mall_v2.0.9_online.apk","fileSize":16056120,"createTime":1545292436968,"versionName":"2.0.9","appLabel":"即有生活","appPkgName":"com.giveu.shoppingmall","appMd5":"26311cb3a5ad8eb899cb942865fde69c","versionCode":"20009"},{"fileName":"mall_v2.0.11_online.apk","fileSize":16693142,"createTime":1546602798568,"versionName":"2.0.11","appLabel":"即有生活","appPkgName":"com.giveu.shoppingmall","appMd5":"df60affea8cab65aff22a531b21292be","versionCode":"20011","commitBy":"张穗旭"},{"fileName":"mall_v2.0.12_online.apk","fileSize":17620004,"createTime":1547060611448,"versionName":"2.0.12","appLabel":"即有生活","appPkgName":"com.giveu.shoppingmall","appMd5":"451c62e76c88ba90c997de0bad8f7f5b","versionCode":"20012","commitBy":"张穗旭"},{"fileName":"3corder_V3.4.10_online.apk","fileSize":26909495,"createTime":1547640825858,"versionName":"3.4.10","appLabel":"即有宝","appPkgName":"com.giveu.corder","appMd5":"0c449a097484db695361e34b0ffa399f","versionCode":"30410","updateContent":"线下分销正式包","commitBy":"heyingjun"},{"fileName":"mall_v2.1.1_online.apk","fileSize":16437995,"createTime":1548053988674,"versionName":"2.1.1","appLabel":"即有生活","appPkgName":"com.giveu.shoppingmall","appMd5":"34567295de6c6686151ee14bbe7a2e46","versionCode":"20101","commitBy":"张穗旭"},{"fileName":"3corder_V3.4.11_online.apk","fileSize":26924720,"createTime":1548319802953,"versionName":"3.4.11","appLabel":"即有宝","appPkgName":"com.giveu.corder","appMd5":"932d31a05581ba35bc468263e1b1718a","versionCode":"30411","updateContent":"正式包bug修复","commitBy":"heyingjun"},{"fileName":"mall_V2.1.2_online.apk","fileSize":18157038,"createTime":1548928261369,"versionName":"2.1.2","appLabel":"即有生活","appPkgName":"com.giveu.shoppingmall","appMd5":"7916a31236bdd1eba8a8a057e11afee3","versionCode":"20102","updateContent":"这是正式版本2.1.2的包","commitBy":"zhulanting"},{"fileName":"smobile_v1.0.5_online.apk","fileSize":7789312,"createTime":1548992645881,"versionName":"1.0.5","appLabel":"购机宝","appPkgName":"com.giveu.smobile","appMd5":"53c66d3a010dea7bdc2685c299ab75ee","versionCode":"10005","commitBy":"zhulanting"},{"fileName":"vcard_V1.0.7.2_test.apk","fileSize":32748054,"createTime":1550802440114,"versionName":"1.0.7.2","appLabel":"MyGiveU","appPkgName":"com.giveu.vcard","appMd5":"e502adea481f67203ed7380917e4f72b","versionCode":"10006","updateContent":"修复不能上传身份证图片问题","commitBy":"zhulanting"},{"fileName":"mall_v2.1.4_online.apk","fileSize":16516510,"createTime":1551943294994,"versionName":"2.1.4","appLabel":"即有生活","appPkgName":"com.giveu.shoppingmall","appMd5":"d08ff0d4c4c93a0c5254d04d043d63d5","versionCode":"20104","commitBy":"张穗旭"},{"fileName":"vcard_V1.0.7_online.apk","fileSize":31421053,"createTime":1552463838447,"versionName":"1.0.7","appLabel":"MyGiveU","appPkgName":"com.giveu.vcard","appMd5":"77177fad9acebbe2314c5c702be151c1","versionCode":"10007","updateContent":"1.工行sdk升级版本","commitBy":"zhulanting"},{"fileName":"mall_v2.1.5_online.apk","fileSize":16826435,"createTime":1553132553052,"versionName":"2.1.5","appLabel":"即有生活","appPkgName":"com.giveu.shoppingmall","appMd5":"7c19c952fae5826671fef52a7dc43517","versionCode":"20105","updateContent":"3月21上线正式包","commitBy":"张穗旭"},{"fileName":"mall_v2.1.6_online.apk","fileSize":17556691,"createTime":1554256791031,"versionName":"2.1.6","appLabel":"即有生活","appPkgName":"com.giveu.shoppingmall","appMd5":"0b1dc61ce40e7ec54e6adbe945b54e56","versionCode":"20106","updateContent":"汇聚支付，改名，铜板街迁移 正式包","commitBy":"张穗旭"},{"fileName":"mall_v2.1.8_online.apk","fileSize":17808852,"createTime":1557022960351,"versionName":"2.1.8","appLabel":"即有生活","appPkgName":"com.giveu.shoppingmall","appMd5":"f84a9b668081a9dfd627f8d3b0f05b35","versionCode":"20108","updateContent":"红岭上架包","commitBy":"张穗旭"},{"fileName":"mall_V2.1.9_online.apk","fileSize":19049763,"createTime":1557311017510,"versionName":"2.1.9","appLabel":"即有生活","appPkgName":"com.giveu.shoppingmall","appMd5":"45edf51faf7790878ad70d96584b0493","versionCode":"20109","updateContent":"vip权益礼包正式包","commitBy":"贺英俊"},{"fileName":"mall_v2.1.10_online.apk","fileSize":18270042,"createTime":1557716000901,"versionName":"2.1.10","appLabel":"即有生活","appPkgName":"com.giveu.shoppingmall","appMd5":"2282bb7db0382199926b8ac541f2339e","versionCode":"20110","updateContent":"上架即速用和vip权益礼包需求","commitBy":"zhulanting"},{"fileName":"mall_v2.1.11_online.apk","fileSize":18241177,"createTime":1559109912071,"versionName":"2.1.11","appLabel":"即有生活","appPkgName":"com.giveu.shoppingmall","appMd5":"c6907801067e7538c780b3e7882d89ec","versionCode":"20111","updateContent":"小马\u0026桔子上线包（应用宝）","commitBy":"贺英俊"},{"fileName":"mall_v2.1.12_online.apk","fileSize":19016851,"createTime":1559313970132,"versionName":"2.1.12","appLabel":"即有生活","appPkgName":"com.giveu.shoppingmall","appMd5":"9f1ed56ce2afef33443c91333874e4a3","versionCode":"20112","commitBy":"毕遥兵"},{"fileName":"cunicomsa_v1.0.3_online.apk","fileSize":8413466,"createTime":1560234021662,"versionName":"1.0.3","appLabel":"享有宝","appPkgName":"com.giveu.cunicomsa","appMd5":"3d02fe927295480ff8c6a8abe365215e","versionCode":"10003","commitBy":"taojunming"},{"fileName":"smobile_v1.1.3_online.apk","fileSize":8306755,"createTime":1560234021903,"versionName":"1.1.3","appLabel":"购机宝","appPkgName":"com.giveu.smobile","appMd5":"c31dbc8bc24d1243f21dc62bea17a8b7","versionCode":"10103","commitBy":"taojunming"},{"fileName":"cmobile_v1.2.4_online.apk","fileSize":39441765,"createTime":1560480498457,"versionName":"1.2.4","appLabel":"中移金服","appPkgName":"com.giveu.cmobile","appMd5":"21029881fc9d08a37daadd515a2cab6d","versionCode":"10204","commitBy":"taojunming"},{"fileName":"cunicomsa_v1.0.4_online.apk","fileSize":8413466,"createTime":1560480499290,"versionName":"1.0.4","appLabel":"享有宝","appPkgName":"com.giveu.cunicomsa","appMd5":"466f43ed64988e0f06241819415854f1","versionCode":"10004","commitBy":"taojunming"},{"fileName":"smobile_v1.1.4_online.apk","fileSize":8306755,"createTime":1560480499574,"versionName":"1.1.4","appLabel":"购机宝","appPkgName":"com.giveu.smobile","appMd5":"50a339b7ba668ae23adc58c69530e527","versionCode":"10104","commitBy":"taojunming"},{"fileName":"mall_v2.1.14_online.apk","fileSize":18269866,"createTime":1560765304886,"versionName":"2.1.14","appLabel":"即有生活","appPkgName":"com.giveu.shoppingmall","appMd5":"ec69700464cc5301f780df6dd88c7252","versionCode":"20114","updateContent":"包商切桔子\n还款\n(已加固正式包)","commitBy":"张穗旭"},{"fileName":"cunicom_v1.0.3_online.apk","fileSize":37662567,"createTime":1560929379288,"versionName":"1.0.3","appLabel":"享购机","appPkgName":"com.giveu.cunicom","appMd5":"c69e4f1af40d26a6229f8a8fcf568ef3","versionCode":"10003","updateContent":"享购机预审需求正式包","commitBy":"贺英俊"},{"fileName":"cmobile_v1.2.5_online.apk","fileSize":39445861,"createTime":1560938736053,"versionName":"1.2.5","appLabel":"中移金服","appPkgName":"com.giveu.cmobile","appMd5":"9a5b4c3aa6f2fee18613652693f14bed","versionCode":"10205","commitBy":"taojunming"},{"fileName":"mall_v2.1.15_online.apk","fileSize":19110850,"createTime":1561021830759,"versionName":"2.1.15","appLabel":"即有生活","appPkgName":"com.giveu.shoppingmall","appMd5":"8c03781f8c3dfa2b129a15bc1cac20ad","versionCode":"20115","updateContent":"即速用3期和拒件（线上环境）","commitBy":"毕遥兵"},{"fileName":"cunicom_v1.0.4_online.apk","fileSize":37662567,"createTime":1561372947216,"versionName":"1.0.4","appLabel":"享购机","appPkgName":"com.giveu.cunicom","appMd5":"518931e862ab240dbc7eea658d915406","versionCode":"10004","updateContent":"享购机姓名限制需求正式包","commitBy":"贺英俊"},{"fileName":"cunicom_v1.0.5_online.apk","fileSize":37662567,"createTime":1561543182442,"versionName":"1.0.5","appLabel":"享购机","appPkgName":"com.giveu.cunicom","appMd5":"84ef2d781421eaf1a3b8067137e19d59","versionCode":"10005","updateContent":"删除代扣卡需求正式包","commitBy":"贺英俊"},{"fileName":"mall_v2.1.16_online.apk","fileSize":19111390,"createTime":1561545800408,"versionName":"2.1.16","appLabel":"即有生活","appPkgName":"com.giveu.shoppingmall","appMd5":"74599c88babc9a446efe9b6d59b44eb2","versionCode":"20116","updateContent":"桔子分期\n桔子满额度\nv5客服\n正式加固包","commitBy":"张穗旭"},{"fileName":"mall_v2.1.17_online.apk","fileSize":18358186,"createTime":1561718783152,"versionName":"2.1.17","appLabel":"即有生活","appPkgName":"com.giveu.shoppingmall","appMd5":"c49308697fa4bed9cf41832aed05aaae","versionCode":"20117","updateContent":"正式加固包","commitBy":"张穗旭"},{"fileName":"cmobile_v1.2.6_online.apk","fileSize":26703791,"createTime":1562141647822,"versionName":"1.2.6","appLabel":"中移金服","appPkgName":"com.giveu.cmobile","appMd5":"56fa6a427720c195cc0383f628a1c5d9","versionCode":"10206","updateContent":"中移金服更换商汤sdk正式环境","commitBy":"贺英俊"},{"fileName":"mall_v2.1.18_online.apk","fileSize":19121950,"createTime":1562320305460,"versionName":"2.1.18","appLabel":"即有生活","appPkgName":"com.giveu.shoppingmall","appMd5":"d56b54115d39c513955856dabd99d3cd","versionCode":"20118","updateContent":"即速用0701需求","commitBy":"毕遥兵"},{"fileName":"cunicomsa_v1.0.5_online.apk","fileSize":9123262,"createTime":1562747294972,"versionName":"1.0.5","appLabel":"享有宝","appPkgName":"com.giveu.cunicomsa","appMd5":"ac6f553957f6cc807e9e2e088f06fc9d","versionCode":"10005","updateContent":"享有宝商户签约需求正式包","commitBy":"贺英俊"},{"fileName":"cunicom_v1.0.6_online.apk","fileSize":17856442,"createTime":1562854413068,"versionName":"1.0.6","appLabel":"享购机","appPkgName":"com.giveu.cunicom","appMd5":"b925f4fbb54bb81438b7b5e07e21bf04","versionCode":"10006","commitBy":"贺英俊"},{"fileName":"mall_v2.1.19_online.apk","fileSize":19122519,"createTime":1563158367779,"versionName":"2.1.19","appLabel":"即有生活","appPkgName":"com.giveu.shoppingmall","appMd5":"ddae69c947f6759c030aadb0f8376802","versionCode":"20119","commitBy":"张穗旭"},{"fileName":"cunicom_v1.0.7_online.apk","fileSize":17852346,"createTime":1563433226952,"versionName":"1.0.7","appLabel":"享购机","appPkgName":"com.giveu.cunicom","appMd5":"58c813b922fd1907393224045ccc92e2","versionCode":"10007","commitBy":"贺英俊"},{"fileName":"mall_v2.1.20_online.apk","fileSize":19246018,"createTime":1563529760678,"versionName":"2.1.20","appLabel":"即有生活","appPkgName":"com.giveu.shoppingmall","appMd5":"3dedffe3a33cb32ada52156c7e9ccac1","versionCode":"20120","commitBy":"taojunming"},{"fileName":"cmobile_v1.2.7_online.apk","fileSize":11911684,"createTime":1564049639408,"versionName":"1.2.7","appLabel":"中移金服","appPkgName":"com.giveu.cmobile","appMd5":"cf79a55b30e3ed30ba9e5d4e13a81391","versionCode":"10207","commitBy":"贺英俊"},{"fileName":"cunicom_v1.0.8_online.apk","fileSize":17614797,"createTime":1564049639842,"versionName":"1.0.8","appLabel":"享购机","appPkgName":"com.giveu.cunicom","appMd5":"093cf51bca1a27a55f1dcd3ab511a304","versionCode":"10008","commitBy":"贺英俊"},{"fileName":"cunicomsa_v1.0.7_online.apk","fileSize":9119166,"createTime":1564049640157,"versionName":"1.0.7","appLabel":"享有宝","appPkgName":"com.giveu.cunicomsa","appMd5":"98aec907848be4dc1f93557caa801780","versionCode":"10007","commitBy":"贺英俊"},{"fileName":"smobile_v1.1.5_online.apk","fileSize":8302659,"createTime":1564049640465,"versionName":"1.1.5","appLabel":"购机宝","appPkgName":"com.giveu.smobile","appMd5":"11bfc9b1db804178b77ae0ee1ab8878c","versionCode":"10105","commitBy":"贺英俊"},{"fileName":"mall_v2.1.21_online.apk","fileSize":20186880,"createTime":1564142692878,"versionName":"2.1.21","appLabel":"即有生活","appPkgName":"com.giveu.shoppingmall","appMd5":"85c0e13a50b6d5d189af2cb09c4e82ae","versionCode":"20121","commitBy":"taojunming"},{"fileName":"cunicom_v1.0.9_online.apk","fileSize":17627085,"createTime":1565091266987,"versionName":"1.0.9","appLabel":"享购机","appPkgName":"com.giveu.cunicom","appMd5":"2d56048bcd6d5a175f8227bdce026d6d","versionCode":"10009","updateContent":"大众租赁上线","commitBy":"贺英俊"},{"fileName":"cmobile_v1.2.8_online.apk","fileSize":11883012,"createTime":1565168418916,"versionName":"1.2.8","appLabel":"中移金服","appPkgName":"com.giveu.cmobile","appMd5":"ee38e8c5496f08e110d72e66b33fdb89","versionCode":"10208","commitBy":"贺英俊"},{"fileName":"cunicom_v1.1.0_online.apk","fileSize":17631181,"createTime":1565168419373,"versionName":"1.1.0","appLabel":"享购机","appPkgName":"com.giveu.cunicom","appMd5":"08ccc55e17c0a7ddbba35c612050ac2b","versionCode":"10100","commitBy":"贺英俊"},{"fileName":"cunicomsa_v1.0.8_online.apk","fileSize":9119166,"createTime":1565168419689,"versionName":"1.0.8","appLabel":"享有宝","appPkgName":"com.giveu.cunicomsa","appMd5":"70550d8e806bf85128c553ec315ddfa6","versionCode":"10008","commitBy":"贺英俊"},{"fileName":"cunicomsa_v1.0.9_online.apk","fileSize":5881633,"createTime":1565602345003,"versionName":"1.0.9","appLabel":"享有宝","appPkgName":"com.giveu.cunicomsa","appMd5":"06b306813adfb63fd1bee25255e81dcc","versionCode":"10009","updateContent":"数据分离上线包","commitBy":"贺英俊"},{"fileName":"mall_v2.1.23.2_release.apk","fileSize":20187357,"createTime":1565834136296,"versionName":"2.1.23.2","appLabel":"即有生活","appPkgName":"com.giveu.shoppingmall","appMd5":"43ffc3dc607d66b3aa235cefb50761d0","versionCode":"20121","commitBy":"毕遥兵"},{"fileName":"mall_v2.1.22_online.apk","fileSize":20200605,"createTime":1566195668481,"versionName":"2.1.22","appLabel":"即有生活","appPkgName":"com.giveu.shoppingmall","appMd5":"d23af359c47a9753b9f52fcd568546e0","versionCode":"20122","updateContent":"未加固版上架包","commitBy":"张穗旭"},{"fileName":"mall_v2.1.23_online.apk","fileSize":19774949,"createTime":1566298111770,"versionName":"2.1.23","appLabel":"即有生活","appPkgName":"com.giveu.shoppingmall","appMd5":"a279906c60ee236142ab3f7be6d1700d","versionCode":"20123","commitBy":"张穗旭"},{"fileName":"cmobile_v1.2.9_online.apk","fileSize":11787788,"createTime":1566378375855,"versionName":"1.2.9","appLabel":"中移金服","appPkgName":"com.giveu.cmobile","appMd5":"e81c509ec985d8965ccae364eb15a949","versionCode":"10209","updateContent":"现网4期 增加销户正式包","commitBy":"贺英俊"},{"fileName":"cunicom_v1.1.1_online.apk","fileSize":17523669,"createTime":1566379110235,"versionName":"1.1.1","appLabel":"享购机","appPkgName":"com.giveu.cunicom","appMd5":"4523027305248b7dcfa582b6409f2415","versionCode":"10101","updateContent":"现网4期销户正式包","commitBy":"贺英俊"},{"fileName":"cunicomsa_v1.1.1_online.apk","fileSize":14926116,"createTime":1566395507276,"versionName":"1.1.1","appLabel":"享有宝","appPkgName":"com.giveu.cunicomsa","appMd5":"b7ab03b8518649777c70e4e39d0f6c9a","versionCode":"10101","commitBy":"taojunming"},{"fileName":"cunicomsa_v1.1.3_online.apk","fileSize":15243731,"createTime":1566450835166,"versionName":"1.1.3","appLabel":"享有宝","appPkgName":"com.giveu.cunicomsa","appMd5":"bf560be44378ae525ad97111ac6360be","versionCode":"10103","commitBy":"taojunming"},{"fileName":"cunicomsa_v1.1.4_online.apk","fileSize":14926116,"createTime":1566452596738,"versionName":"1.1.4","appLabel":"享有宝","appPkgName":"com.giveu.cunicomsa","appMd5":"dc91dff23e44e1ebb11fd4a9784306b4","versionCode":"10104","commitBy":"taojunming"},{"fileName":"cunicomsa_v1.1.5_online.apk","fileSize":14934308,"createTime":1566491834137,"versionName":"1.1.5","appLabel":"享有宝","appPkgName":"com.giveu.cunicomsa","appMd5":"ff068431ff80e5766f8eee92cbc4bd18","versionCode":"10105","commitBy":"taojunming"},{"fileName":"cunicomsa_v1.1.6_online.apk","fileSize":14934308,"createTime":1566496262761,"versionName":"1.1.6","appLabel":"享有宝","appPkgName":"com.giveu.cunicomsa","appMd5":"cf86ef08fb456a2663420643854d44cc","versionCode":"10106","commitBy":"taojunming"},{"fileName":"cmobile_1.2.9.3_test.apk","fileSize":13079451,"createTime":1566892490209,"versionName":"1.2.9.3","appLabel":"中移金服","appPkgName":"com.giveu.cmobile","appMd5":"70ae834ef8631653d3b115a551c41b31","versionCode":"10208","commitBy":"taojunming"},{"fileName":"cunicom_v1.1.2_online.apk","fileSize":17531861,"createTime":1566981902276,"versionName":"1.1.2","appLabel":"享购机","appPkgName":"com.giveu.cunicom","appMd5":"96bce2597a86153f7a7ac5e0e743ad6f","versionCode":"10102","commitBy":"taojunming"},{"fileName":"cmobile_v1.3.0.1_test.apk","fileSize":12976832,"createTime":1566984605495,"versionName":"1.3.0.1","appLabel":"中移金服","appPkgName":"com.giveu.cmobile","appMd5":"7c688dc3b3d6f412e20028b24f929b6a","versionCode":"10300","commitBy":"taojunming"},{"fileName":"smobile_v1.1.6_online.apk","fileSize":5453235,"createTime":1566984786534,"versionName":"1.1.6","appLabel":"购机宝","appPkgName":"com.giveu.smobile","appMd5":"b7f7a47f6958e2d0c14e360801027912","versionCode":"10106","commitBy":"贺英俊"},{"fileName":"cunicomsa_v1.1.7_online.apk","fileSize":14896425,"createTime":1566984858037,"versionName":"1.1.7","appLabel":"享有宝","appPkgName":"com.giveu.cunicomsa","appMd5":"59ca1bce50584e7945f7715f2ea87d58","versionCode":"10107","commitBy":"贺英俊"},{"fileName":"cmobile_v1.3.0_online.apk","fileSize":11791884,"createTime":1566985003485,"versionName":"1.3.0","appLabel":"中移金服","appPkgName":"com.giveu.cmobile","appMd5":"f8ac5b5500f12f7fc941415f657a0c90","versionCode":"10300","commitBy":"taojunming"},{"fileName":"cunicomsa_v1.1.8_online.apk","fileSize":14904617,"createTime":1567424257200,"versionName":"1.1.8","appLabel":"享有宝","appPkgName":"com.giveu.cunicomsa","appMd5":"7a007587214d42e7f5a90e38bdd28ad8","versionCode":"10108","commitBy":"taojunming"},{"fileName":"cmobile_v1.3.1.1_test.apk","fileSize":16177050,"createTime":1567751475218,"versionName":"1.3.1.1","appLabel":"中移金服","appPkgName":"com.giveu.cmobile","appMd5":"f80c373782facf8a09484c98bc37e018","versionCode":"10301","commitBy":"taojunming"},{"fileName":"mall_v2.1.24_online.apk","fileSize":20114938,"createTime":1567758115258,"versionName":"2.1.24","appLabel":"即有生活","appPkgName":"com.giveu.shoppingmall","appMd5":"8adda8e9279b4b391df5ff55ada42658","versionCode":"20124","updateContent":"星辰2期需求\n绑卡中断流程优化需求\n飞贷即时用资方风控需求\n启动页增加授权声明\n债转需求","commitBy":"张穗旭"},{"fileName":"smobile_v1.1.7_online.apk","fileSize":5698995,"createTime":1568019716762,"versionName":"1.1.7","appLabel":"购机宝","appPkgName":"com.giveu.smobile","appMd5":"3e05760ccb6a500d3e15707d0ef58671","versionCode":"10107","commitBy":"taojunming"},{"fileName":"cmobile_v1.3.1_online.apk","fileSize":14791222,"createTime":1568103868994,"versionName":"1.3.1","appLabel":"中移金服","appPkgName":"com.giveu.cmobile","appMd5":"85c9575d3ddf2a0a91f739b708198a1f","versionCode":"10301","commitBy":"taojunming"},{"fileName":"mall_v2.1.25_online.apk","fileSize":19317605,"createTime":1568249365402,"versionName":"2.1.25","appLabel":"即有生活","appPkgName":"com.giveu.shoppingmall","appMd5":"7376ece346dbd931108ab1c4caab39b6","versionCode":"20125","updateContent":"爬虫下架需求-加固包","commitBy":"张穗旭"},{"fileName":"cunicomsa_v1.1.9_online.apk","fileSize":14875945,"createTime":1568802849527,"versionName":"1.1.9","appLabel":"享有宝","appPkgName":"com.giveu.cunicomsa","appMd5":"7e50510a2c67b17e988777cdb75d069c","versionCode":"10109","commitBy":"贺英俊"},{"fileName":"smobile_v1.1.8_online.apk","fileSize":5682611,"createTime":1568802850008,"versionName":"1.1.8","appLabel":"购机宝","appPkgName":"com.giveu.smobile","appMd5":"0970082124571e5178dfefa94bfb7274","versionCode":"10108","commitBy":"贺英俊"},{"fileName":"cmobile_v1.3.1.2_test.apk","fileSize":16178030,"createTime":1568864566611,"versionName":"1.3.1.2","appLabel":"中移金服","appPkgName":"com.giveu.cmobile","appMd5":"f05f901e27a7e77bbd88dfbbf6d1dd59","versionCode":"10301","commitBy":"taojunming"},{"fileName":"mall_v2.1.27_online.apk","fileSize":19628247,"createTime":1568896538882,"versionName":"2.1.27","appLabel":"即有生活","appPkgName":"com.giveu.shoppingmall","appMd5":"8e1a034b0e725e8684485185c8d69aa6","versionCode":"20127","updateContent":"资金路由2期","commitBy":"张穗旭"},{"fileName":"cunicom_v1.1.3_online.apk","fileSize":17523669,"createTime":1568967667186,"versionName":"1.1.3","appLabel":"享购机","appPkgName":"com.giveu.cunicom","appMd5":"c0b7d5058727b63f27500245b1f3cf13","versionCode":"10103","commitBy":"taojunming"},{"fileName":"mall_v2.1.26_online.apk","fileSize":20114974,"createTime":1569230314990,"versionName":"2.1.26","appLabel":"即有生活","appPkgName":"com.giveu.shoppingmall","appMd5":"59b6543ac44898ab80f4a7877782a028","versionCode":"20126","updateContent":"即速用支付渠道改造","commitBy":"毕遥兵"},{"fileName":"smobile_v1.2.0.1_test.apk","fileSize":12819518,"createTime":1569576381582,"versionName":"1.2.0.1","appLabel":"购机宝","appPkgName":"com.giveu.smobile","appMd5":"792119ddb6f2ecc83570239bf0840168","versionCode":"10200","commitBy":"taojunming"},{"fileName":"smobile_v1.2.0.2_test.apk","fileSize":12812673,"createTime":1569811206764,"versionName":"1.2.0.2","appLabel":"购机宝","appPkgName":"com.giveu.smobile","appMd5":"d7e7e43ca7ac48f51ef5344e63755cfb","versionCode":"10200","commitBy":"贺英俊"},{"fileName":"cunicomsa_v1.2.1_online.apk","fileSize":14971391,"createTime":1570525652409,"versionName":"1.2.1","appLabel":"享有宝","appPkgName":"com.giveu.cunicomsa","appMd5":"b28b8f469e6ead6cde251ec7b2025822","versionCode":"10201","commitBy":"taojunming"},{"fileName":"smobile_v1.2.0_online.apk","fileSize":11663425,"createTime":1570525652705,"versionName":"1.2.0","appLabel":"购机宝","appPkgName":"com.giveu.smobile","appMd5":"51d1b13f425fe78b342aaebf8775865f","versionCode":"10200","commitBy":"taojunming"},{"fileName":"3corder_V3.5.0_online.apk","fileSize":27626470,"createTime":1570789889193,"versionName":"3.5.0","appLabel":"即有宝","appPkgName":"com.giveu.corder","appMd5":"a5a6a447198243427380364d6b513303","versionCode":"30500","commitBy":"贺英俊"},{"fileName":"3corder_V3.5.1_online.apk","fileSize":27628505,"createTime":1571127381018,"versionName":"3.5.1","appLabel":"即有宝","appPkgName":"com.giveu.corder","appMd5":"cf132bb4580df75b4636237756f4b93a","versionCode":"30501","commitBy":"贺英俊"},{"fileName":"3corder_V3.5.2_online.apk","fileSize":28313905,"createTime":1571135680175,"versionName":"3.5.2","appLabel":"即有宝","appPkgName":"com.giveu.corder","appMd5":"34ccb355879ad4f6dd5522b67b4d0882","versionCode":"30501","commitBy":"贺英俊"},{"fileName":"mall_v2.2.0_online.apk","fileSize":19251910,"createTime":1571648877111,"versionName":"2.2.0","appLabel":"即有生活","appPkgName":"com.giveu.shoppingmall","appMd5":"c8e53e765a9c95db05a869d13c0e68ab","versionCode":"20200","commitBy":"毕遥兵"},{"fileName":"mall_v2.2.1_online.apk","fileSize":19223389,"createTime":1572339367683,"versionName":"2.2.1","appLabel":"即有生活","appPkgName":"com.giveu.shoppingmall","appMd5":"42ed2f6d2f5122a567c1dc4de9d994cf","versionCode":"20201","updateContent":"用户中心二期上线","commitBy":"zhulanting"},{"fileName":"mall_v2.2.2_online.apk","fileSize":19244290,"createTime":1572947387667,"versionName":"2.2.2","appLabel":"即有生活","appPkgName":"com.giveu.shoppingmall","appMd5":"c1864d72ab94092ff641f6b40ffbf921","versionCode":"20202","updateContent":"免息券和红包还款上线","commitBy":"zhulanting"},{"fileName":"smobile_v1.2.1.1_test.apk","fileSize":12823372,"createTime":1573180490080,"versionName":"1.2.1.1","appLabel":"购机宝","appPkgName":"com.giveu.smobile","appMd5":"716ae571c33e92fdcb6f86f41d7f3dd9","versionCode":"10201","commitBy":"taojunming"},{"fileName":"smobile_v1.2.1.3_test.apk","fileSize":12823357,"createTime":1573698825932,"versionName":"1.2.1.3","appLabel":"购机宝","appPkgName":"com.giveu.smobile","appMd5":"6679ebc40d1c6b15551e34604f8745e4","versionCode":"10201","commitBy":"taojunming"},{"fileName":"smobile_v1.2.1.4_test.apk","fileSize":12823354,"createTime":1573718898568,"versionName":"1.2.1.4","appLabel":"购机宝","appPkgName":"com.giveu.smobile","appMd5":"f69e887c67c104960eb3a8d8afd5d1a0","versionCode":"10201","commitBy":"taojunming"},{"fileName":"smobile_v1.2.1.5_test.apk","fileSize":12823664,"createTime":1573722463974,"versionName":"1.2.1.5","appLabel":"购机宝","appPkgName":"com.giveu.smobile","appMd5":"2928c80baed8355482a0add25cfa91bf","versionCode":"10201","commitBy":"taojunming"},{"fileName":"smobile_v1.2.1.6_test.apk","fileSize":12823829,"createTime":1573787497976,"versionName":"1.2.1.6","appLabel":"购机宝","appPkgName":"com.giveu.smobile","appMd5":"bc49cf0b5804044170103047dcd8b974","versionCode":"10201","commitBy":"taojunming"},{"fileName":"cmobile_v1.3.2.2_test.apk","fileSize":16180916,"createTime":1574219773004,"versionName":"1.3.2.2","appLabel":"中移金服","appPkgName":"com.giveu.cmobile","appMd5":"56aea584eba1d81f19a91c3328136919","versionCode":"10302","commitBy":"taojunming"},{"fileName":"mall_v2.2.3.9_test.apk","fileSize":19085815,"createTime":1574243635622,"versionName":"2.2.3.9","appLabel":"即有生活","appPkgName":"com.giveu.shoppingmall","appMd5":"97403406e21b9f49dbf16cb27a66d8c6","versionCode":"20202","updateContent":"综合测试版本","commitBy":"zhulanting"},{"fileName":"mall_v2.2.3.10_test.apk","fileSize":19034483,"createTime":1574330826530,"versionName":"2.2.3.10","appLabel":"即有生活","appPkgName":"com.giveu.shoppingmall","appMd5":"89095ddf6b384a74a2e83fef983c6e85","versionCode":"20202","updateContent":"优化还款显示额度","commitBy":"zhulanting"},{"fileName":"cmobile_v1.3.2.3_test.apk","fileSize":16181132,"createTime":1574332411101,"versionName":"1.3.2.3","appLabel":"中移金服","appPkgName":"com.giveu.cmobile","appMd5":"1f77f6c742d6f5dd0c484417ae665af5","versionCode":"10302","commitBy":"taojunming"},{"fileName":"mall_v2.2.3_online.apk","fileSize":19034527,"createTime":1574335140493,"versionName":"2.2.3","appLabel":"即有生活","appPkgName":"com.giveu.shoppingmall","appMd5":"f96f5983d91856f2edc5724a3383d591","versionCode":"20203","updateContent":"1.V2.2.3版本上线\n2.即速用借款红包上线\n3.洽客风控+循环授信上线","commitBy":"zhulanting"},{"fileName":"mall_v2.3.0.1_test.apk","fileSize":19034119,"createTime":1575016800708,"versionName":"2.3.0.1","appLabel":"即有生活","appPkgName":"com.giveu.shoppingmall","appMd5":"78857dac694ee013a6c87ece01739ab7","versionCode":"20203","updateContent":"用户3期需求提测\n","commitBy":"zhulanting"},{"fileName":"mall_v2.2.4.1_test.apk","fileSize":19034159,"createTime":1575255861667,"versionName":"2.2.4.1","appLabel":"即有生活","appPkgName":"com.giveu.shoppingmall","appMd5":"30f274bb469f56f8137a5edcadb61390","versionCode":"20203","updateContent":"修复即速用申请跳转贷超页面空白问题","commitBy":"zhulanting"},{"fileName":"qkkj_v4.0.0_normal_online.apk","fileSize":25096653,"createTime":1575285741019,"versionName":"4.0.0","appLabel":"爱用商城","appPkgName":"com.qkkj.wallet","appMd5":"6cb96371f901652c0ff936cfa4577d4f","versionCode":"40000","updateContent":"4.0.0版本上线\n1.更换双十二图标\n2.好人会员卡功能上线","commitBy":"zhulanting"},{"fileName":"mall_v2.2.4.1_2_test.apk","fileSize":19034155,"createTime":1575364962601,"versionName":"2.2.4.1","appLabel":"即有生活","appPkgName":"com.giveu.shoppingmall","appMd5":"a232321873d6b7b062b5db8c5fe7b582","versionCode":"20203","updateContent":"更新征信授权书链接","commitBy":"zhulanting"},{"fileName":"mall_v2.2.4.2_test.apk","fileSize":19033403,"createTime":1575441881809,"versionName":"2.2.4.2","appLabel":"即有生活","appPkgName":"com.giveu.shoppingmall","appMd5":"4dee8d5359c94e56fe85af459a55d7ba","versionCode":"20203","updateContent":"1.去掉登录页面注册入口\n2.优化个人中心未激活提示","commitBy":"zhulanting"},{"fileName":"topactivity1.apk","fileSize":1820772,"createTime":1575596451694,"versionName":"1.0","appLabel":"TopActivity","appPkgName":"com.example.zlt.topactivity","appMd5":"37949ed28f50bc3d5380e28dfebcc4ec","versionCode":"1","updateContent":"test","commitBy":"zhulanting"},{"fileName":"cmobile_v1.3.2.4_1_test.apk","fileSize":22583040,"createTime":1575624622843,"versionName":"1.3.2.4","appLabel":"中移金服","appPkgName":"com.giveu.cmobile","appMd5":"8ff87171a87363085b800044cc8a0708","versionCode":"10302","commitBy":"zhulanting"},{"fileName":"cunicomsa_v1.2.2.11_test_1.apk","fileSize":13313815,"createTime":1575881819438,"versionName":"1.2.2.11","appLabel":"享有宝","appPkgName":"com.giveu.cunicomsa","appMd5":"e88b487fb3a2c5b729dc208fe2ec101e","versionCode":"10202","updateContent":"新包","commitBy":"taojunming"},{"fileName":"smobile_v1.2.1.7_test.apk","fileSize":12981165,"createTime":1575971980649,"versionName":"1.2.1.7","appLabel":"购机宝","appPkgName":"com.giveu.smobile","appMd5":"82429cdb9d2829c1c2a493d05990a0db","versionCode":"10201","commitBy":"taojunming"},{"fileName":"giveu_market_v5.1_release.apk","fileSize":3634754,"createTime":1576227307431,"versionName":"5.1","appLabel":"即有市场","appPkgName":"com.giveu.downloader","appMd5":"942d9589ef2b883b82aca33ef61700f3","versionCode":"2","updateContent":"最新版本，新增爱用日志","commitBy":"zhulanting"},{"fileName":"cunicom_v1.1.4_online.apk","fileSize":15042864,"createTime":1576237208013,"versionName":"1.1.4","appLabel":"享购机","appPkgName":"com.giveu.cunicom","appMd5":"268e8e77e411c062817b79a30820fe9c","versionCode":"10104","commitBy":"taojunming"},{"fileName":"cunicomsa_v1.2.2_online.apk","fileSize":11771962,"createTime":1576237208290,"versionName":"1.2.2","appLabel":"享有宝","appPkgName":"com.giveu.cunicomsa","appMd5":"953c5fde5146ae8a817f48b3344e7a3c","versionCode":"10202","commitBy":"taojunming"},{"fileName":"smobile_v1.2.1_online.apk","fileSize":11477798,"createTime":1576237208570,"versionName":"1.2.1","appLabel":"购机宝","appPkgName":"com.giveu.smobile","appMd5":"c9eac8a399a4875ec2e82135b83d5eac","versionCode":"10201","commitBy":"taojunming"},{"fileName":"cmobile_v1.3.2_online.apk","fileSize":20751578,"createTime":1576238178640,"versionName":"1.3.2","appLabel":"中移金服","appPkgName":"com.giveu.cmobile","appMd5":"7f7ad35e13c4fb6172294e6ef665d3cd","versionCode":"10302","commitBy":"taojunming"},{"fileName":"qkkj_v4.1.0_normal_online.apk","fileSize":25220004,"createTime":1576639791107,"versionName":"4.1.0","appLabel":"爱用商城","appPkgName":"com.qkkj.wallet","appMd5":"b93add4cb3e178beba6fefd9ae8caa7b","versionCode":"41000","updateContent":"4.1.0版本上线\n1、增加预付定金预售功能","commitBy":"zhulanting"},{"fileName":"qkkj_v4.1.1_normal_online.apk","fileSize":25321667,"createTime":1576757921021,"versionName":"4.1.1","appLabel":"爱用商城","appPkgName":"com.qkkj.wallet","appMd5":"d04d6dbbf77d24765c5a6a02da482187","versionCode":"41001","commitBy":"zhulanting"},{"fileName":"mall_v2.2.5.3_test.apk","fileSize":16794450,"createTime":1577259470393,"versionName":"2.2.5.3","appLabel":"绿信钱包","appPkgName":"com.giveu.shoppingmall","appMd5":"cb9d5c20e6b02d8e9a62a302010c473b","versionCode":"20204","commitBy":"张穗旭"},{"fileName":"mall_v2.3.0_online.apk","fileSize":15348723,"createTime":1577265174007,"versionName":"2.3.0","appLabel":"绿信钱包","appPkgName":"com.giveu.shoppingmall","appMd5":"18a8b6a0bd971a2d28db65c45110cda2","versionCode":"20300","commitBy":"张穗旭"},{"fileName":"mall_v2.2.4_online.apk","fileSize":15342346,"createTime":1577341864684,"versionName":"2.2.4","appLabel":"即有生活","appPkgName":"com.giveu.shoppingmall","appMd5":"f27092bb7b66aec48b083fa2ab1082ea","versionCode":"20204","commitBy":"张穗旭"},{"fileName":"cmobile_v1.3.3.1_test.apk","fileSize":22583351,"createTime":1578392238927,"versionName":"1.3.3.1","appLabel":"中移金服","appPkgName":"com.giveu.cmobile","appMd5":"cb398e094a80a7883e2a394af820a735","versionCode":"10303","commitBy":"taojunming"},{"fileName":"cmobile_v1.3.3.2_test.apk","fileSize":22583486,"createTime":1578468766382,"versionName":"1.3.3.2","appLabel":"中移金服","appPkgName":"com.giveu.cmobile","appMd5":"c630a0e23402670a78fb23f4066a45e5","versionCode":"10303","commitBy":"taojunming"},{"fileName":"mall_v2.2.6_online.apk","fileSize":15839594,"createTime":1579067196093,"versionName":"2.2.6","appLabel":"绿信钱包","appPkgName":"com.giveu.shoppingmall","appMd5":"a5dd370192563da71de56df0672db52f","versionCode":"20206","updateContent":"绿信钱包线上环境","commitBy":"zhulanting"},{"fileName":"mall_v2.2.6.1_test.apk","fileSize":15839490,"createTime":1579071022149,"versionName":"2.2.6.1","appLabel":"绿信钱包","appPkgName":"com.giveu.shoppingmall","appMd5":"22e05dfa8231c4cd92f3f9636fca9b8c","versionCode":"20206","updateContent":"绿信钱包最新版","commitBy":"zhulanting"},{"fileName":"mall_v2.2.5.2_dev.apk","fileSize":15667104,"createTime":1579155832029,"versionName":"2.2.5.2","appLabel":"即有生活","appPkgName":"com.giveu.shoppingmall","appMd5":"953ec4b169556fbe5b04e6eca0dac5dd","versionCode":"20205","updateContent":"给周剩的测试版本","commitBy":"zhulanting"},{"fileName":"mall_v2.2.6.2_test.apk","fileSize":15835830,"createTime":1579230602344,"versionName":"2.2.6.2","appLabel":"绿信科技","appPkgName":"com.lvxin.shoppingmall","appMd5":"117ff24c691c2b93f12b7c3c5fbe9953","versionCode":"20206","updateContent":"绿信接腾讯云活体OCR","commitBy":"zhulanting"},{"fileName":"mall_v2.2.6.3_test.apk","fileSize":15830735,"createTime":1579428195918,"versionName":"2.2.6.3","appLabel":"绿信科技","appPkgName":"com.lvxin.shoppingmall","appMd5":"921f740c039d29c22e88b0b964e776cc","versionCode":"20206","updateContent":"更新订单详情消费分期合同链接\n更新关于钱包界面图标","commitBy":"zhulanting"},{"fileName":"giveu_market_v5.2_release.apk","fileSize":3635050,"createTime":1579489764442,"versionName":"5.2","appLabel":"即有市场","appPkgName":"com.giveu.downloader","appMd5":"976eb7c45bcc3f0bd18fe08b996ee168","versionCode":"2","updateContent":"1.修复日志不实时显示的bug\n2.新增点击图标复制下载地址的隐藏功能","commitBy":"zhulanting"},{"fileName":"jxh_v1.0.0.1_test.apk","fileSize":20119577,"createTime":1587432248810,"versionName":"1.0.0.1","appLabel":"吉享花","appPkgName":"com.lvxin.jxh","appMd5":"18ae453e23d3681418486be2d7c2e3fa","versionCode":"43000","updateContent":"吉享花需求提测","commitBy":"zhulanting"},{"fileName":"jxh_v1.0.0.2_dev.apk","fileSize":21561553,"createTime":1587544514556,"versionName":"1.0.0.2","appLabel":"吉享花","appPkgName":"com.lvxin.jxh","appMd5":"4bdec0c5bc5b7886da83e10c0673ba83","versionCode":"10000","commitBy":"zhulanting"},{"fileName":"jxh_v1.0.0.3_test.apk","fileSize":21561646,"createTime":1587546805183,"versionName":"1.0.0.3","appLabel":"吉享花","appPkgName":"com.lvxin.jxh","appMd5":"aaa5dec6fc461cd9b2c6200f4d2192bb","versionCode":"10000","commitBy":"zhulanting"},{"fileName":"cunicomsa_v1.2.4.1_test.apk","fileSize":14048655,"createTime":1587715569585,"versionName":"1.2.4.1","appLabel":"享有宝","appPkgName":"com.giveu.cunicomsa","appMd5":"76208555e9b443dc89469b86c1d52788","versionCode":"10204","commitBy":"taojunming"},{"fileName":"jxh_v1.0.0.6_dev.apk","fileSize":21564202,"createTime":1587973216270,"versionName":"1.0.0.6","appLabel":"吉享花","appPkgName":"com.lvxin.jxh","appMd5":"9635c60610e994c54d56225d596cf72f","versionCode":"10000","commitBy":"zhulanting"},{"fileName":"giveu_market_v5.3_release.apk","fileSize":3634954,"createTime":1588060292911,"versionName":"5.3","appLabel":"即有市场","appPkgName":"com.giveu.downloader","appMd5":"52935f59e549167379f74d1ca95ce9de","versionCode":"2","updateContent":"更新吉享花日志系统","commitBy":"zhulanting"},{"fileName":"cunicomsa_v1.2.4_online.apk","fileSize":12747324,"createTime":1588151517167,"versionName":"1.2.4","appLabel":"享有宝","appPkgName":"com.giveu.cunicomsa","appMd5":"2b6148d5780e78fd70a3bfc7e69a8d45","versionCode":"10204","commitBy":"taojunming"},{"fileName":"jxh_v1.0.0.8_test.apk","fileSize":21553839,"createTime":1588212944748,"versionName":"1.0.0.8","appLabel":"吉享花","appPkgName":"com.lvxin.jxh","appMd5":"9a491c095479ae49d3b43d3864b92e13","versionCode":"10000","updateContent":"吉享花最新测试版本","commitBy":"zhulanting"},{"fileName":"jxh_v1.0.0.8_dev.apk","fileSize":22317006,"createTime":1588314718019,"versionName":"1.0.0.8","appLabel":"吉享花","appPkgName":"com.lvxin.jxh","appMd5":"e8d20ec544860595c03b75049bbfde42","versionCode":"10000","updateContent":"To 雪芳 NEW","commitBy":"zhulanting"},{"fileName":"jxh_v1.0.0.10_test.apk","fileSize":22334181,"createTime":1588501874992,"versionName":"1.0.0.10","appLabel":"吉享花","appPkgName":"com.lvxin.jxh","appMd5":"9ae9213e4c5e31af77d7ee1e6bb9f486","versionCode":"10000","updateContent":"1.接入微信支付\n2.bug修复","commitBy":"zhulanting"},{"fileName":"jxh_v1.0.0.12_test.apk","fileSize":22754348,"createTime":1588922025217,"versionName":"1.0.0.12","appLabel":"吉享花","appPkgName":"com.lvxin.jxh","appMd5":"5fb06d2600e9d2fea19144951a4e2606","versionCode":"10000","updateContent":"bug修复","commitBy":"zhulanting"},{"fileName":"cunicomsa_v1.2.5_online.apk","fileSize":12755876,"createTime":1589019582292,"versionName":"1.2.5","appLabel":"享有宝","appPkgName":"com.giveu.cunicomsa","appMd5":"d7c5e2fcf64e2d3eb0157eb234010dfd","versionCode":"10205","commitBy":"taojunming"},{"fileName":"jxh_v1.0.0_online.apk","fileSize":21229598,"createTime":1589193826924,"versionName":"1.0.0","appLabel":"吉享花","appPkgName":"com.lvxin.jxh","appMd5":"d2449b791285baa80b9bd17878f001d1","versionCode":"10000","updateContent":"1.ui优化\n2.爱满分支付改吉享分支付\n3.修改授信挽留提示语","commitBy":"zhulanting"},{"fileName":"mall_v2.2.9.1_test.apk","fileSize":15677115,"createTime":1589878296387,"versionName":"2.2.9.1","appLabel":"即有生活","appPkgName":"com.giveu.shoppingmall","appMd5":"ebe1aa524d9c81155448230515b0d261","versionCode":"20209","updateContent":"还款支付方式动态配置","commitBy":"zhulanting"},{"fileName":"mall_v2.2.9.2_test.apk","fileSize":15677015,"createTime":1589890989246,"versionName":"2.2.9.2","appLabel":"即有生活","appPkgName":"com.giveu.shoppingmall","appMd5":"f3108b366f39c21587802758fb4c2704","versionCode":"20209","updateContent":"旧版本","commitBy":"zhulanting"},{"fileName":"cunicomsa_v1.2.6_online.apk","fileSize":12755876,"createTime":1589968728711,"versionName":"1.2.6","appLabel":"享有宝","appPkgName":"com.giveu.cunicomsa","appMd5":"b2b6de8453ccbedb1ae4571b1a634f89","versionCode":"10206","commitBy":"taojunming"},{"fileName":"jxh_v1.0.1.1_test.apk","fileSize":20807140,"createTime":1590024324488,"versionName":"1.0.1.1","appLabel":"吉享花","appPkgName":"com.lvxin.jxh","appMd5":"0fc11d2f0b7dbe0b00aaaad9c93203d1","versionCode":"11000","updateContent":"合约引流弹窗需求","commitBy":"zhulanting"},{"fileName":"jxh_v1.1.0_online.apk","fileSize":21629561,"createTime":1591350315754,"versionName":"1.1.0","appLabel":"吉享花","appPkgName":"com.lvxin.jxh","appMd5":"5c5bea7a1b8c9c29fd56eb16da9afe0d","versionCode":"11000","updateContent":"还款需求上线版本","commitBy":"zhulanting"},{"fileName":"jxh_v1.1.1_online.apk","fileSize":21387625,"createTime":1593428576758,"versionName":"1.1.1","appLabel":"吉享花","appPkgName":"com.lvxin.jxh","appMd5":"76bd44f123ed4e7e527237bd0669325b","versionCode":"11100","commitBy":"zhulanting"},{"fileName":"jxh_v1.1.2.4_test.apk","fileSize":24855632,"createTime":1594008199753,"versionName":"1.1.2.4","appLabel":"吉享花","appPkgName":"com.lvxin.jxh","appMd5":"7760e70466f5262aab11f88017e0a26c","versionCode":"11200","commitBy":"taojunming"},{"fileName":"jxh_v1.1.2.5_test.apk","fileSize":24854188,"createTime":1594118682518,"versionName":"1.1.2.5","appLabel":"吉享花","appPkgName":"com.lvxin.jxh","appMd5":"31ee0ceb8b7f3e49e8275229574cfe2f","versionCode":"11200","commitBy":"taojunming"},{"fileName":"jxh_v1.1.2.6_test.apk","fileSize":24854788,"createTime":1594203005761,"versionName":"1.1.2.6","appLabel":"吉享花","appPkgName":"com.lvxin.jxh","appMd5":"604e43d4e895bf9e90486a4cdac010ed","versionCode":"11200","commitBy":"taojunming"},{"fileName":"jxh_v1.1.2.7_test.apk","fileSize":24854191,"createTime":1594367180747,"versionName":"1.1.2.7","appLabel":"吉享花","appPkgName":"com.lvxin.jxh","appMd5":"37f30641054baf2ed36a11ffa1a58849","versionCode":"11200","commitBy":"taojunming"},{"fileName":"jxh_v1.1.2.8_test.apk","fileSize":21387743,"createTime":1594369592622,"versionName":"1.1.2.8","appLabel":"吉享花","appPkgName":"com.lvxin.jxh","appMd5":"e3063e6001973e9f95a611649bc43348","versionCode":"11200","updateContent":"信用购机账单","commitBy":"zhulanting"},{"fileName":"jxh_v1.1.2.9_test.apk","fileSize":24854171,"createTime":1594374136423,"versionName":"1.1.2.9","appLabel":"吉享花","appPkgName":"com.lvxin.jxh","appMd5":"08e59169d22404a80724fd608f7d8d1a","versionCode":"11200","commitBy":"taojunming"},{"fileName":"jxh_v1.1.2.10_test.apk","fileSize":22641472,"createTime":1594621929270,"versionName":"1.1.2.10","appLabel":"吉享花","appPkgName":"com.lvxin.jxh","appMd5":"1e5c48c84dcde824110d312e1c561e21","versionCode":"11200","updateContent":"修复合约机用户刷脸界面协议显示不正确问题","commitBy":"zhulanting"},{"fileName":"jxh_v1.1.2.11_test.apk","fileSize":22640769,"createTime":1594954301023,"versionName":"1.1.2.11","appLabel":"吉享花","appPkgName":"com.lvxin.jxh","appMd5":"5d9aaa84c705dc00c476f603363813c9","versionCode":"11200","updateContent":"首页添加信用购入口","commitBy":"zhulanting"},{"fileName":"cunicomsa_v1.2.7.12_test.apk","fileSize":14027879,"createTime":1595213080616,"versionName":"1.2.7.12","appLabel":"享有宝","appPkgName":"com.giveu.cunicomsa","appMd5":"8b9927fa81a143994ee414d5b5bfdc59","versionCode":"10207","commitBy":"taojunming"},{"fileName":"cunicomsa_v1.2.7_online.apk","fileSize":12801942,"createTime":1595237568576,"versionName":"1.2.7","appLabel":"享有宝","appPkgName":"com.giveu.cunicomsa","appMd5":"0697dad28c863a8e8a8802032731f085","versionCode":"10207","commitBy":"taojunming"},{"fileName":"qkkj_v4.5.0_normal_online.apk","fileSize":19615923,"createTime":1596105982852,"versionName":"4.5.0","appLabel":"爱用商城","appPkgName":"com.qkkj.wallet","appMd5":"3cafb9faa95432827d2f9c5468b607ec","versionCode":"45000","commitBy":"zhulanting"},{"fileName":"qkkj_v4.5.1_normal_online.apk","fileSize":19364674,"createTime":1596802716926,"versionName":"4.5.1","appLabel":"爱用商城","appPkgName":"com.qkkj.wallet","appMd5":"5cdb1eea174f6226600385c24f04bd89","versionCode":"45100","updateContent":"收银台优化需求","commitBy":"zhulanting"},{"fileName":"qkkj_v4.5.2.1_test.apk","fileSize":19937903,"createTime":1598956118654,"versionName":"4.5.2.1","appLabel":"爱用商城","appPkgName":"com.qkkj.wallet","appMd5":"94d210e4788a9100cf7fc85c85387426","versionCode":"45200","updateContent":"一键登录测试版本","commitBy":"zhulanting"},{"fileName":"qkkj_v4.5.2.2_test.apk","fileSize":19942072,"createTime":1599120245538,"versionName":"4.5.2.2","appLabel":"爱用商城","appPkgName":"com.qkkj.wallet","appMd5":"79197e77b23c577af0993a1aa59fe165","versionCode":"45200","updateContent":"修复一键登录非默认登录方式问题\n修复收银台显示不正确问题","commitBy":"zhulanting"},{"fileName":"qkkj_v4.5.2.3_test.apk","fileSize":19980266,"createTime":1599218421193,"versionName":"4.5.2.3","appLabel":"爱用商城","appPkgName":"com.qkkj.wallet","appMd5":"a7ad8bf49e022def496b404fd8b3497a","versionCode":"45200","updateContent":"bug修复版本","commitBy":"zhulanting"},{"fileName":"qkkj_v4.5.2.4_normal_test.apk","fileSize":23081467,"createTime":1599442141371,"versionName":"4.5.2.4","appLabel":"爱用商城","appPkgName":"com.qkkj.wallet","appMd5":"fa2264f731a7a8489c59ce3a053e082b","versionCode":"45200","updateContent":"修复银行卡默认显示信用卡问题\n修复下单登录默认非一键登录问题\n修复其他问题","commitBy":"zhulanting"},{"fileName":"qkkj_v4.5.2.5_normal_test.apk","fileSize":23082101,"createTime":1599447201399,"versionName":"4.5.2.5","appLabel":"爱用商城","appPkgName":"com.qkkj.wallet","appMd5":"8ccbb9a635b82b9a5939cd7a9bb1788c","versionCode":"45200","updateContent":"修改还款详情UI样式\n修复收银台分期服务费展示不对问题","commitBy":"zhulanting"},{"fileName":"qkkj_v4.5.2.6_test.apk","fileSize":23082133,"createTime":1599460931472,"versionName":"4.5.2.6","appLabel":"爱用商城","appPkgName":"com.qkkj.wallet","appMd5":"7bfc5a94c468b331a2048d30f631e7cf","versionCode":"45200","commitBy":"zhulanting"},{"fileName":"qkkj_v4.5.2.7_normal_test.apk","fileSize":23082392,"createTime":1599463809024,"versionName":"4.5.2.7","appLabel":"爱用商城","appPkgName":"com.qkkj.wallet","appMd5":"335fadf03a0a0c0a8d7f5d5e1aea1d7a","versionCode":"45200","updateContent":"验证实名成功返回继续支付问题","commitBy":"zhulanting"},{"fileName":"qkkj_v4.5.2.8_normal_test.apk","fileSize":23081946,"createTime":1599471048629,"versionName":"4.5.2.8","appLabel":"爱用商城","appPkgName":"com.qkkj.wallet","appMd5":"fb1038d9c00fcbb1afc8e494ec2279d4","versionCode":"45200","updateContent":"修复实名返回支付异常问题","commitBy":"zhulanting"},{"fileName":"qkkj_v4.5.2_normal_online.apk","fileSize":20174345,"createTime":1599614448486,"versionName":"4.5.2","appLabel":"爱用商城","appPkgName":"com.qkkj.wallet","appMd5":"2a6b6fe98607fa11779d513fe374bf39","versionCode":"45200","commitBy":"zhulanting"},{"fileName":"jxh_v1.1.3.2_test.apk","fileSize":26094156,"createTime":1600842279316,"versionName":"1.1.3.2","appLabel":"吉享花","appPkgName":"com.lvxin.jxh","appMd5":"b697ac3fce3345cff76d865285cb661b","versionCode":"11300","updateContent":"登录注册添加埋点","commitBy":"zhulanting"},{"fileName":"jxh_v1.1.3.3_test.apk","fileSize":26093903,"createTime":1600917755576,"versionName":"1.1.3.3","appLabel":"吉享花","appPkgName":"com.lvxin.jxh","appMd5":"ed2961afd23654ab5cbaa3b4388e1307","versionCode":"11300","updateContent":"修复授信界面埋点上传兼容性异常问题","commitBy":"zhulanting"},{"fileName":"jxh_v1.1.3.4_test.apk","fileSize":25611800,"createTime":1600929593961,"versionName":"1.1.3.4","appLabel":"吉享花","appPkgName":"com.lvxin.jxh","appMd5":"dc590cbea6e80ed488b2e1bdf61cdf76","versionCode":"11300","updateContent":"授信埋点bug修复","commitBy":"zhulanting"},{"fileName":"jxh_v1.1.3.5_test.apk","fileSize":26095020,"createTime":1601023919947,"versionName":"1.1.3.5","appLabel":"吉享花","appPkgName":"com.lvxin.jxh","appMd5":"6258578f0086a1762a799fa414487f8c","versionCode":"11300","updateContent":"修改通讯录变量一些统计规则","commitBy":"zhulanting"},{"fileName":"qkkj_v4.5.3.1_test.apk","fileSize":25196653,"createTime":1601342684728,"versionName":"4.5.3.1","appLabel":"爱用商城","appPkgName":"com.qkkj.wallet","appMd5":"d05c70a1acef99e7ef55f021b59b476e","versionCode":"45300","updateContent":"广告需求 test","commitBy":"zhulanting"},{"fileName":"qkkj_v4.5.3.2_test.apk","fileSize":21400201,"createTime":1601429862557,"versionName":"4.5.3.2","appLabel":"爱用商城","appPkgName":"com.qkkj.wallet","appMd5":"ee9b75af19d4906be27d1df5390bf8f7","versionCode":"45300","updateContent":"广告接入bug修复版本","commitBy":"zhulanting"},{"fileName":"qkkj_v4.5.3.6_normal_test.apk","fileSize":21492056,"createTime":1602670549940,"versionName":"4.5.3.6","appLabel":"爱用商城","appPkgName":"com.qkkj.wallet","appMd5":"230569f4d98653db6b4253002fd25b29","versionCode":"45300","updateContent":"bug修复及UI优化","commitBy":"zhulanting"},{"fileName":"qkkj_v4.5.4.1_normal_test.apk","fileSize":25283325,"createTime":1604987106338,"versionName":"4.5.4.1","appLabel":"爱用商城","appPkgName":"com.qkkj.wallet","appMd5":"6513d999d42abc27c3e5924d50fbafd2","versionCode":"45400","updateContent":"4.5.4第一版测试","commitBy":"fushaozhen"},{"fileName":"qkkj_v4.5.4.2_normal_test.apk","fileSize":25298263,"createTime":1605162164754,"versionName":"4.5.4.2","appLabel":"爱用商城","appPkgName":"com.qkkj.wallet","appMd5":"e06b01ff318c2620837b49b6db8dd38a","versionCode":"45401","updateContent":"4.5.4第二版测试","commitBy":"fushaozhen"},{"fileName":"qkkj_v4.5.4.3_normal_test.apk","fileSize":25300172,"createTime":1605234960408,"versionName":"4.5.4.3","appLabel":"爱用商城","appPkgName":"com.qkkj.wallet","appMd5":"a418d0c2107132d5d07dd46e45425c47","versionCode":"45400","updateContent":"4.5.4第三版测试","commitBy":"fushaozhen"},{"fileName":"qkkj_v4.5.4.4_normal_test.apk","fileSize":25300801,"createTime":1605246198697,"versionName":"4.5.4.4","appLabel":"爱用商城","appPkgName":"com.qkkj.wallet","appMd5":"b21afb40448c63b45bc18b224fe17ade","versionCode":"45400","updateContent":"sd","commitBy":"fushaozhen"},{"fileName":"qkkj_v4.5.4.5_normal_test.apk","fileSize":25302839,"createTime":1605258400812,"versionName":"4.5.4.5","appLabel":"爱用商城","appPkgName":"com.qkkj.wallet","appMd5":"7dc26cf7305ceb48a0a9511ca317ac24","versionCode":"45400","updateContent":"4.5.4第五版测试","commitBy":"fushaozhen"},{"fileName":"qkkj_v4.5.4.7_normal_test.apk","fileSize":25303716,"createTime":1605492049547,"versionName":"4.5.4.7","appLabel":"爱用商城","appPkgName":"com.qkkj.wallet","appMd5":"2380d17723549ecae71080d0ca202b31","versionCode":"45400","updateContent":"OK了","commitBy":"fushaozhen"},{"fileName":"qkkj_v4.5.5.1_test_debug_v1.apk","fileSize":27096420,"createTime":1611105011166,"versionName":"4.5.5.1","appLabel":"爱用商城","appPkgName":"com.qkkj.wallet","appMd5":"d74f6f17d4cf1e6d30840880c3303850","versionCode":"45510","updateContent":"4.5.5第一版测试","commitBy":"fushaozhen"},{"fileName":"qkkj_v4.5.5.1_normal_test_v2.apk","fileSize":27095909,"createTime":1611126803515,"versionName":"4.5.5.1","appLabel":"爱用商城","appPkgName":"com.qkkj.wallet","appMd5":"7ea9dbe3ad49becc3f5fa789d402b3c1","versionCode":"45510","updateContent":"4.5.5第二版测试","commitBy":"fushaozhen"},{"fileName":"qkkj_v4.5.5.1_normal_test_v3.apk","fileSize":27098775,"createTime":1611215576637,"versionName":"4.5.5.1","appLabel":"爱用商城","appPkgName":"com.qkkj.wallet","appMd5":"2f485056b7da8937e81b0a2dc1c5674a","versionCode":"45510","updateContent":"4.5.5第三版测试","commitBy":"fushaozhen"},{"fileName":"qkkj_v4.5.5.1_normal_test_v4.apk","fileSize":27098486,"createTime":1611222838334,"versionName":"4.5.5.1","appLabel":"爱用商城","appPkgName":"com.qkkj.wallet","appMd5":"d3b01cdc4294b6aa01ff1ded19daf1b3","versionCode":"45510","updateContent":"4.5.5第4版测试","commitBy":"fushaozhen"},{"fileName":"qkkj_v4.5.5.1_normal_test_v5.apk","fileSize":27099069,"createTime":1611285458486,"versionName":"4.5.5.1","appLabel":"爱用商城","appPkgName":"com.qkkj.wallet","appMd5":"10dffe9e5d8ca7247ff0bf467c6aa3ee","versionCode":"45510","updateContent":"4.5.5第五版测试","commitBy":"fushaozhen"},{"fileName":"qkkj_v4.5.5.1_normal_test_v6.apk","fileSize":27098330,"createTime":1611297116318,"versionName":"4.5.5.1","appLabel":"爱用商城","appPkgName":"com.qkkj.wallet","appMd5":"9b717595481d39d6ea55759ab98b7675","versionCode":"45510","updateContent":"4.5.5第6版测试","commitBy":"fushaozhen"},{"fileName":"qkkj_v4.5.5.1_normal_test_v7.apk","fileSize":27098619,"createTime":1611537919704,"versionName":"4.5.5.1","appLabel":"爱用商城","appPkgName":"com.qkkj.wallet","appMd5":"a926a226e08073278d09c53efae4edc8","versionCode":"45510","updateContent":"4.5.5第7版测试","commitBy":"fushaozhen"},{"fileName":"qkkj_v4.5.5.1_normal_test_v8.apk","fileSize":27099173,"createTime":1611568251574,"versionName":"4.5.5.1","appLabel":"爱用商城","appPkgName":"com.qkkj.wallet","appMd5":"784404666ec2bc4aba5957fd218d95ae","versionCode":"45510","updateContent":"4.5.5第八版测试","commitBy":"fushaozhen"},{"fileName":"qkkj_v4.5.5.1_normal_test_v9.apk","fileSize":27099423,"createTime":1611623538523,"versionName":"4.5.5.1","appLabel":"爱用商城","appPkgName":"com.qkkj.wallet","appMd5":"6819f3904f9981f560210702ceb757aa","versionCode":"45510","updateContent":"4.5.5第9版测试","commitBy":"fushaozhen"},{"fileName":"qkkj_v4.5.5.1_normal_test_v10.apk","fileSize":27099525,"createTime":1611626254608,"versionName":"4.5.5.1","appLabel":"爱用商城","appPkgName":"com.qkkj.wallet","appMd5":"05eb85129daf29ca64f071408e88ed08","versionCode":"45510","updateContent":"4.5.5第10版测试","commitBy":"fushaozhen"},{"fileName":"qkkj_v4.5.5.1_borrow_test_v11.apk","fileSize":27099520,"createTime":1611648494704,"versionName":"4.5.5.1","appLabel":"爱用商城","appPkgName":"com.qkkj.wallet","appMd5":"715eb439c71f9af327b5541c4cba6b8b","versionCode":"45510","updateContent":"4.5.5第11版测试","commitBy":"fushaozhen"},{"fileName":"qkkj_v4.5.5.1_borrow_test_v12.apk","fileSize":27099680,"createTime":1611650591511,"versionName":"4.5.5.1","appLabel":"爱用商城","appPkgName":"com.qkkj.wallet","appMd5":"9c3b8fecec12970934c681eed99ff667","versionCode":"45510","updateContent":"4.5.5第12版测试","commitBy":"fushaozhen"},{"fileName":"qkkj_v4.5.5_normal_online.apk","fileSize":22870324,"createTime":1611667133332,"versionName":"4.5.5","appLabel":"爱用商城","appPkgName":"com.qkkj.wallet","appMd5":"e9387ebd729755ae822c0f33566d6668","versionCode":"45510","commitBy":"fushaozhen"},{"fileName":"qkkj_v4.5.6_borrow_test_v1.apk","fileSize":27099171,"createTime":1615530245693,"versionName":"4.5.6","appLabel":"爱用商城","appPkgName":"com.qkkj.wallet","appMd5":"1250c646b3cbe8a216395530e1fc5df7","versionCode":"45510","commitBy":"fushaozhen"},{"fileName":"qkkj_v4.5.6_borrow_test_v2.apk","fileSize":27106447,"createTime":1615962585580,"versionName":"4.5.6","appLabel":"爱用商城","appPkgName":"com.qkkj.wallet","appMd5":"ba03a80609b139e62f3fc12edba400c5","versionCode":"45600","commitBy":"fushaozhen"},{"fileName":"qkkj_v4.5.6_borrow_test_v3.apk","fileSize":27101651,"createTime":1616665428511,"versionName":"4.5.6","appLabel":"爱用商城","appPkgName":"com.qkkj.wallet","appMd5":"2b41f15506b86b0a979f0dbeb446c1b9","versionCode":"45600","updateContent":"1111","commitBy":"fushaozhen"},{"fileName":"qkkj_v4.5.6_borrow_test_v4.apk","fileSize":27110058,"createTime":1616668993513,"versionName":"4.5.6","appLabel":"爱用商城","appPkgName":"com.qkkj.wallet","appMd5":"c9e6002416adbafbc78708106edf6b8b","versionCode":"45600","updateContent":"asa","commitBy":"fushaozhen"},{"fileName":"AyqMall_test.apk","fileSize":26031995,"createTime":1667183107843,"versionName":"v1.0.0","appLabel":"爱享花","appPkgName":"com.ayq.wallet","appMd5":"508004d803fd75e38758fe6317bdc795","versionCode":"1","commitBy":"fushaozhen"}]